Metadata-Version: 2.1
Name: os-signals
Version: 1.0.0
Summary: A simple module for convinient terminal singal sending
Home-page: UNKNOWN
Author: Sjoerd Vermeulen
Author-email: sjoerd@marsenaar.com
License: UNKNOWN
Platform: UNKNOWN
Classifier: Programming Language :: Python :: 3
Classifier: License :: OSI Approved :: MIT License
Classifier: Operating System :: POSIX :: Linux
Requires-Python: >=3.6
